Workbook

Sheet Calculadora Freelance
A1: Operaciones | F1: Gastos Fijos Mensuales
A2: Concepto | B2: Requeridos | C2: Dias de Trabajo | D2: Costo | F2: Concepto | G2: Duracion(Meses) | H2: Costo Mensual | I2: Costo Total
A3: Líder de proyecto | B3: 1 | C3: 30 | D3: =Empleados!D2*C3 -> 45000 | F3: Basicos (Luz, Agua, etc) | G3: 1 | H3: 500 | I3: =G3*H3 -> 500
A4: Científico de datos | B4: 1 | C4: 30 | D4: =Empleados!D3*C4 -> 50000 | F4: Internet | G4: 1 | H4: 500 | I4: =G4*H4 -> 500
A5: Ingeniero de datos (Jr) | B5: 1 | C5: 30 | D5: =Empleados!D4*C5 -> 30000 | F5: Licencias | G5: 1 | H5: 500 | I5: =G5*H5 -> 500
A6: Ingeniero de datos | B6: 0 | C6: 0 | D6: =Empleados!D5*C6 -> 0 | F6: Total | I6: =SUM(H3:H5) -> 1500
A7: Ingeniero de datos (Senior) | B7: 0 | C7: 0 | D7: =Empleados!D6*C7 -> 0
A8: Analista de Datos | B8: 1 | C8: 20 | D8: =Empleados!D7*C8 -> 20000
A9: Total | D9: =SUM(D3:D8) -> 145000
C11: Gastos Operativos | D11: =D9*0.25 -> 36250
C12: Costo total | D12: =SUM(D9+I6+D11) -> 182750

Sheet Cronograma
A1: Semana | B1: Actividades principales | C1: Asignado
A2: 1 | B2: Establecer Requerimientos, KPI's | C2: PO
A3: 1 | B3: Limpieza y exploración de datos, establecimiento de baseline | C3: DE
A4: 2 | B4: Entrenamiento y comparación de modelos predictivos (Random Forest vs LSTM) | C4: DS
A5: 2 | B5: Validación de resultados, construcción de visualizaciones interactivas y análisis | C5: DA
A6: 3 | B6: Elaboración de reportes preeliminares, revisión con expertos | C6: DA
A7: 3 | B7: Revision con Cliente | C7: PO
A8: 4 | B8: Elaboración de reportes finales | C8: DA
A9: 4 | B9: Revisión con expertos, propuesta de acciones | C9: DS
A10: 4 | B10: Entrega | C10: PO

Sheet Empleados
A1: Rol | B1: Sueldo mensual (MXN) | C1: Tiempo estimado (meses) | D1: Costo total Diario (MXN) | E1: ISR | F1: Ingreso Neto
A2: Líder de proyecto | B2: 45000 | C2: 1 | D2: =B2/30 -> 1500 | E2: =B2*0.16 -> 7200 | F2: =B2-E2 -> 37800
A3: Científico de datos | B3: 50000 | C3: 1 | D3: =B3/30 -> 1666.6667 | E3: =B3*0.16 -> 8000 | F3: =B3-E3 -> 42000
A4: Ingeniero de datos (Jr) | B4: 30000 | C4: 1 | D4: =B4/30 -> 1000 | E4: =B4*0.16 -> 4800 | F4: =B4-E4 -> 25200
A5: Ingeniero de datos | B5: 50000 | C5: 0 | D5: =B5/30 -> 1666.6667 | E5: =B5*0.16 -> 8000 | F5: =B5-E5 -> 42000
A6: Ingeniero de datos (Senior) | B6: 70000 | C6: 0 | D6: =B6/30 -> 2333.3333 | E6: =B6*0.16 -> 11200 | F6: =B6-E6 -> 58800
A7: Analista de Datos | B7: 30000 | C7: 1 | D7: =B7/30 -> 1000 | E7: =B7*0.16 -> 4800 | F7: =B7-E7 -> 25200
